[
  {
    "id": "ganesh.somvanshi",
    "email": "ganesh.somvanshi@verveadvisory.com",
    "displayName": "Ganesh Somvanshi",
    "teamId": "team1",
    "isManager": true,
    "clues": {
      "hobbies": [],
      "quirks": [],
      "funFacts": []
    }
  },
  {
    "id": "aditi.jain",
    "email": "aditi.jain@verveadvisory.com",
    "displayName": "Aditi Jain",
    "teamId": "team1",
    "isManager": false,
    "clues": {
      "hobbies": [],
      "quirks": [],
      "funFacts": []
    }
  },
  {
    "id": "palash.somani",
    "email": "palash.somani@verveadvisory.com",
    "displayName": "Palash Somani",
    "teamId": "team1",
    "isManager": false,
    "clues": {
      "hobbies": [],
      "quirks": [],
      "funFacts": []
    }
  },
  {
    "id": "mayank.panchal",
    "email": "mayank.panchal@verveadvisory.com",
    "displayName": "Mayank Panchal",
    "teamId": "team1",
    "isManager": false,
    "clues": {
      "hobbies": [],
      "quirks": [],
      "funFacts": []
    }
  },
  {
    "id": "vaishali.malasi",
    "email": "vaishali.malasi@verveadvisory.com",
    "displayName": "Vaishali Malasi",
    "teamId": "team1",
    "isManager": false,
    "clues": {
      "hobbies": [],
      "quirks": [],
      "funFacts": []
    }
  },
  {
    "id": "viren.sunil.khetani",
    "email": "viren.khetani@verveadvisory.com",
    "displayName": "Viren Sunil Khetani",
    "teamId": "team1",
    "isManager": false,
    "clues": {
      "hobbies": [],
      "quirks": [],
      "funFacts": []
    }
  },
  {
    "id": "tarun.ghumnani",
    "email": "tarun.ghumnani@verveadvisory.com",
    "displayName": "Tarun Ghumnani",
    "teamId": "team1",
    "isManager": false,
    "clues": {
      "hobbies": [],
      "quirks": [],
      "funFacts": []
    }
  },
  {
    "id": "ayush.ghumnani",
    "email": "ayush.ghumnani@verveadvisory.com",
    "displayName": "Ayush Ghumnani",
    "teamId": "team1",
    "isManager": false,
    "clues": {
      "hobbies": [],
      "quirks": [],
      "funFacts": []
    }
  },
  {
    "id": "ritesh.dilip.chaudhari",
    "email": "ritesh.chaudhari@verveadvisory.com",
    "displayName": "Ritesh Dilip Chaudhari",
    "teamId": "team1",
    "isManager": false,
    "clues": {
      "hobbies": [],
      "quirks": [],
      "funFacts": []
    }
  },
  {
    "id": "sakshi.desai",
    "email": "sakshi.desai@verveadvisory.com",
    "displayName": "Sakshi Desai",
    "teamId": "team1",
    "isManager": false,
    "clues": {
      "hobbies": [],
      "quirks": [],
      "funFacts": []
    }
  },
  {
    "id": "laxmi.khandelwal",
    "email": "laxmi.khandelwal@verveadvisory.com",
    "displayName": "Laxmi Khandelwal",
    "teamId": "team2",
    "isManager": true,
    "clues": {
      "hobbies": [],
      "quirks": [],
      "funFacts": []
    }
  },
  {
    "id": "reena.agrawal",
    "email": "reena.agrawal@verveadvisory.com",
    "displayName": "Reena Agrawal",
    "teamId": "team2",
    "isManager": false,
    "clues": {
      "hobbies": [],
      "quirks": [],
      "funFacts": []
    }
  },
  {
    "id": "aman.jalan",
    "email": "aman.jalan@verveadvisory.com",
    "displayName": "Aman Jalan",
    "teamId": "team2",
    "isManager": false,
    "clues": {
      "hobbies": [],
      "quirks": [],
      "funFacts": []
    }
  },
  {
    "id": "tanvi.agrawal",
    "email": "tanvi.agrawal@verveadvisory.com",
    "displayName": "Tanvi Agrawal",
    "teamId": "team2",
    "isManager": false,
    "clues": {
      "hobbies": [],
      "quirks": [],
      "funFacts": []
    }
  },
  {
    "id": "sumair",
    "email": "sumair@verveadvisory.com",
    "displayName": "Sumair",
    "teamId": "team2",
    "isManager": false,
    "clues": {
      "hobbies": [],
      "quirks": [],
      "funFacts": []
    }
  },
  {
    "id": "rohan.patil",
    "email": "rohan.patil@verveadvisory.com",
    "displayName": "Rohan Patil",
    "teamId": "team2",
    "isManager": false,
    "clues": {
      "hobbies": [],
      "quirks": [],
      "funFacts": []
    }
  },
  {
    "id": "akshata.kolekar",
    "email": "akshata.kolekar@verveadvisory.com",
    "displayName": "Akshata Kolekar",
    "teamId": "team2",
    "isManager": false,
    "clues": {
      "hobbies": [],
      "quirks": [],
      "funFacts": []
    }
  },
  {
    "id": "pushpa.mourya",
    "email": "pushpa.mourya@verveadvisory.com",
    "displayName": "Pushpa Mourya",
    "teamId": "team2",
    "isManager": false,
    "clues": {
      "hobbies": [],
      "quirks": [],
      "funFacts": []
    }
  },
  {
    "id": "asmita.sanjay.lawate",
    "email": "asmita.lawate@verveadvisory.com",
    "displayName": "Asmita Sanjay Lawate",
    "teamId": "team2",
    "isManager": false,
    "clues": {
      "hobbies": [],
      "quirks": [],
      "funFacts": []
    }
  },
  {
    "id": "balaji.prabhu.shinde",
    "email": "balaji.shinde@verveadvisory.com",
    "displayName": "Balaji Prabhu Shinde",
    "teamId": "team2",
    "isManager": false,
    "clues": {
      "hobbies": [],
      "quirks": [],
      "funFacts": []
    }
  },
  {
    "id": "neethu",
    "email": "neethu@verveadvisory.com",
    "displayName": "Neethu",
    "teamId": "team2",
    "isManager": false,
    "clues": {
      "hobbies": [],
      "quirks": [],
      "funFacts": []
    }
  },
  {
    "id": "krutanjali.patil",
    "email": "krutanjali.patil@verveadvisory.com",
    "displayName": "Krutanjali Patil",
    "teamId": "team3",
    "isManager": true,
    "clues": {
      "hobbies": [],
      "quirks": [],
      "funFacts": []
    }
  },
  {
    "id": "fiza.rizvi",
    "email": "fiza.rizvi@verveadvisory.com",
    "displayName": "Fiza Rizvi",
    "teamId": "team3",
    "isManager": false,
    "clues": {
      "hobbies": [],
      "quirks": [],
      "funFacts": []
    }
  },
  {
    "id": "shubham.kothari",
    "email": "shubham.kothari@verveadvisory.com",
    "displayName": "Shubham Kothari",
    "teamId": "team3",
    "isManager": false,
    "clues": {
      "hobbies": [],
      "quirks": [],
      "funFacts": []
    }
  },
  {
    "id": "vaishnavee.kalantri",
    "email": "vaishnavee.kalantri@verveadvisory.com",
    "displayName": "Vaishnavee Kalantri",
    "teamId": "team3",
    "isManager": false,
    "clues": {
      "hobbies": [],
      "quirks": [],
      "funFacts": []
    }
  },
  {
    "id": "radhika.rathi",
    "email": "radhika.rathi@verveadvisory.com",
    "displayName": "Radhika Rathi",
    "teamId": "team3",
    "isManager": false,
    "clues": {
      "hobbies": [],
      "quirks": [],
      "funFacts": []
    }
  },
  {
    "id": "sayam.doshi",
    "email": "sayam.doshi@verveadvisory.com",
    "displayName": "Sayam Doshi",
    "teamId": "team3",
    "isManager": false,
    "clues": {
      "hobbies": [],
      "quirks": [],
      "funFacts": []
    }
  },
  {
    "id": "amol.bibwe",
    "email": "amol.bibwe@verveadvisory.com",
    "displayName": "Amol Bibwe",
    "teamId": "team3",
    "isManager": false,
    "clues": {
      "hobbies": [],
      "quirks": [],
      "funFacts": []
    }
  },
  {
    "id": "abhishek.sonar",
    "email": "abhishek.sonar@verveadvisory.com",
    "displayName": "Abhishek Sonar",
    "teamId": "team3",
    "isManager": false,
    "clues": {
      "hobbies": [],
      "quirks": [],
      "funFacts": []
    }
  },
  {
    "id": "vishakha.jat",
    "email": "vishakha.jat@verveadvisory.com",
    "displayName": "Vishakha Jat",
    "teamId": "team3",
    "isManager": false,
    "clues": {
      "hobbies": [],
      "quirks": [],
      "funFacts": []
    }
  },
  {
    "id": "viren.sunil.khetani-2",
    "email": "viren.khetani@verveadvisory.com",
    "displayName": "Viren Sunil Khetani",
    "teamId": "team3",
    "isManager": false,
    "clues": {
      "hobbies": [],
      "quirks": [],
      "funFacts": []
    }
  },
  {
    "id": "prem.duseja",
    "email": "prem.duseja@verveadvisory.com",
    "displayName": "Prem Duseja",
    "teamId": "team4",
    "isManager": true,
    "clues": {
      "hobbies": [],
      "quirks": [],
      "funFacts": []
    }
  },
  {
    "id": "sima.jain",
    "email": "sima.jain@verveadvisory.com",
    "displayName": "Sima Jain",
    "teamId": "team4",
    "isManager": false,
    "clues": {
      "hobbies": [],
      "quirks": [],
      "funFacts": []
    }
  },
  {
    "id": "pranay.oswal",
    "email": "pranay.oswal@verveadvisory.com",
    "displayName": "Pranay Oswal",
    "teamId": "team4",
    "isManager": false,
    "clues": {
      "hobbies": [],
      "quirks": [],
      "funFacts": []
    }
  },
  {
    "id": "kajal.kale",
    "email": "kajal.kale@verveadvisory.com",
    "displayName": "Kajal Kale",
    "teamId": "team4",
    "isManager": false,
    "clues": {
      "hobbies": [],
      "quirks": [],
      "funFacts": []
    }
  },
  {
    "id": "ansari.matiullah.ziyaullah",
    "email": "ansari.ziyaullah@verveadvisory.com",
    "displayName": "Ansari Matiullah Ziyaullah",
    "teamId": "team4",
    "isManager": false,
    "clues": {
      "hobbies": [],
      "quirks": [],
      "funFacts": []
    }
  },
  {
    "id": "aditya.agrawal",
    "email": "aditya.agrawal@verveadvisory.com",
    "displayName": "Aditya Agrawal",
    "teamId": "team4",
    "isManager": false,
    "clues": {
      "hobbies": [],
      "quirks": [],
      "funFacts": []
    }
  },
  {
    "id": "shubham.dhanawade",
    "email": "shubham.dhanawade@verveadvisory.com",
    "displayName": "Shubham Dhanawade",
    "teamId": "team4",
    "isManager": false,
    "clues": {
      "hobbies": [],
      "quirks": [],
      "funFacts": []
    }
  },
  {
    "id": "prashant.sir",
    "email": "prashant.sir@verveadvisory.com",
    "displayName": "Prashant Sir",
    "teamId": "team4",
    "isManager": false,
    "clues": {
      "hobbies": [],
      "quirks": [],
      "funFacts": []
    }
  },
  {
    "id": "komal.kere",
    "email": "komal.kere@verveadvisory.com",
    "displayName": "Komal Kere",
    "teamId": "team4",
    "isManager": false,
    "clues": {
      "hobbies": [],
      "quirks": [],
      "funFacts": []
    }
  },
  {
    "id": "muskan.daswani",
    "email": "muskan.daswani@verveadvisory.com",
    "displayName": "Muskan Daswani",
    "teamId": "team4",
    "isManager": false,
    "clues": {
      "hobbies": [],
      "quirks": [],
      "funFacts": []
    }
  },
  {
    "id": "shweta.ghumnani",
    "email": "shweta.ghumnani@verveadvisory.com",
    "displayName": "Shweta Ghumnani",
    "teamId": "team5",
    "isManager": true,
    "clues": {
      "hobbies": [],
      "quirks": [],
      "funFacts": []
    }
  },
  {
    "id": "namrata.patil",
    "email": "namrata.patil@verveadvisory.com",
    "displayName": "Namrata Patil",
    "teamId": "team5",
    "isManager": false,
    "clues": {
      "hobbies": [],
      "quirks": [],
      "funFacts": []
    }
  },
  {
    "id": "vidhi.khandelwal",
    "email": "vidhi.khandelwal@verveadvisory.com",
    "displayName": "Vidhi Khandelwal",
    "teamId": "team5",
    "isManager": false,
    "clues": {
      "hobbies": [],
      "quirks": [],
      "funFacts": []
    }
  },
  {
    "id": "mansavi.more",
    "email": "mansavi.more@verveadvisory.com",
    "displayName": "Mansavi More",
    "teamId": "team5",
    "isManager": false,
    "clues": {
      "hobbies": [],
      "quirks": [],
      "funFacts": []
    }
  },
  {
    "id": "shrikar.moolya",
    "email": "shrikar.moolya@verveadvisory.com",
    "displayName": "Shrikar Moolya",
    "teamId": "team5",
    "isManager": false,
    "clues": {
      "hobbies": [],
      "quirks": [],
      "funFacts": []
    }
  },
  {
    "id": "meenal.suke",
    "email": "meenal.suke@verveadvisory.com",
    "displayName": "Meenal Suke",
    "teamId": "team5",
    "isManager": false,
    "clues": {
      "hobbies": [],
      "quirks": [],
      "funFacts": []
    }
  },
  {
    "id": "preet.khandelwal",
    "email": "preet.khandelwal@verveadvisory.com",
    "displayName": "Preet Khandelwal",
    "teamId": "team5",
    "isManager": false,
    "clues": {
      "hobbies": [],
      "quirks": [],
      "funFacts": []
    }
  },
  {
    "id": "mahadev.thawani",
    "email": "mahadev.thawani@verveadvisory.com",
    "displayName": "Mahadev Thawani",
    "teamId": "team5",
    "isManager": false,
    "clues": {
      "hobbies": [],
      "quirks": [],
      "funFacts": []
    }
  },
  {
    "id": "harshita.rajput",
    "email": "harshita.rajput@verveadvisory.com",
    "displayName": "Harshita Rajput",
    "teamId": "team5",
    "isManager": false,
    "clues": {
      "hobbies": [],
      "quirks": [],
      "funFacts": []
    }
  },
  {
    "id": "arya.magar",
    "email": "arya.magar@verveadvisory.com",
    "displayName": "Arya Magar",
    "teamId": "team5",
    "isManager": false,
    "clues": {
      "hobbies": [],
      "quirks": [],
      "funFacts": []
    }
  },
  {
    "id": "harsh.jain",
    "email": "harsh.jain@verveadvisory.com",
    "displayName": "Harsh Jain",
    "teamId": "team6",
    "isManager": true,
    "clues": {
      "hobbies": [],
      "quirks": [],
      "funFacts": []
    }
  },
  {
    "id": "avani.vijay",
    "email": "avani.vijay@verveadvisory.com",
    "displayName": "Avani Vijay",
    "teamId": "team6",
    "isManager": false,
    "clues": {
      "hobbies": [],
      "quirks": [],
      "funFacts": []
    }
  },
  {
    "id": "priyanka.mantri",
    "email": "priyanka.mantri@verveadvisory.com",
    "displayName": "Priyanka Mantri",
    "teamId": "team6",
    "isManager": false,
    "clues": {
      "hobbies": [],
      "quirks": [],
      "funFacts": []
    }
  },
  {
    "id": "aditi.singh",
    "email": "aditi.singh@verveadvisory.com",
    "displayName": "Aditi Singh",
    "teamId": "team6",
    "isManager": false,
    "clues": {
      "hobbies": [],
      "quirks": [],
      "funFacts": []
    }
  },
  {
    "id": "sakshi.ghodke",
    "email": "sakshi.ghodke@verveadvisory.com",
    "displayName": "Sakshi Ghodke",
    "teamId": "team6",
    "isManager": false,
    "clues": {
      "hobbies": [],
      "quirks": [],
      "funFacts": []
    }
  },
  {
    "id": "harsha.rajput",
    "email": "harsha.rajput@verveadvisory.com",
    "displayName": "Harsha Rajput",
    "teamId": "team6",
    "isManager": false,
    "clues": {
      "hobbies": [],
      "quirks": [],
      "funFacts": []
    }
  },
  {
    "id": "arya.magar-2",
    "email": "arya.magar@verveadvisory.com",
    "displayName": "Arya Magar",
    "teamId": "team6",
    "isManager": false,
    "clues": {
      "hobbies": [],
      "quirks": [],
      "funFacts": []
    }
  },
  {
    "id": "gagandeep.singh",
    "email": "gagandeep.singh@verveadvisory.com",
    "displayName": "Gagandeep Singh",
    "teamId": "team6",
    "isManager": false,
    "clues": {
      "hobbies": [],
      "quirks": [],
      "funFacts": []
    }
  },
  {
    "id": "debarima.paul",
    "email": "debarima.paul@verveadvisory.com",
    "displayName": "Debarima Paul",
    "teamId": "team6",
    "isManager": false,
    "clues": {
      "hobbies": [],
      "quirks": [],
      "funFacts": []
    }
  },
  {
    "id": "rukaiya.rangoonwala",
    "email": "rukaiya.rangoonwala@verveadvisory.com",
    "displayName": "Rukaiya Rangoonwala",
    "teamId": "team7",
    "isManager": true,
    "clues": {
      "hobbies": [],
      "quirks": [],
      "funFacts": []
    }
  },
  {
    "id": "ronit.dilip.jadhav",
    "email": "ronit.jadhav@verveadvisory.com",
    "displayName": "Ronit Dilip Jadhav",
    "teamId": "team7",
    "isManager": false,
    "clues": {
      "hobbies": [],
      "quirks": [],
      "funFacts": []
    }
  },
  {
    "id": "vikaram.bhist",
    "email": "vikaram.bhist@verveadvisory.com",
    "displayName": "Vikaram Bhist",
    "teamId": "team7",
    "isManager": false,
    "clues": {
      "hobbies": [],
      "quirks": [],
      "funFacts": []
    }
  },
  {
    "id": "shashank.channawar",
    "email": "shashank.channawar@verveadvisory.com",
    "displayName": "Shashank Channawar",
    "teamId": "team7",
    "isManager": false,
    "clues": {
      "hobbies": [],
      "quirks": [],
      "funFacts": []
    }
  },
  {
    "id": "harshvardhan.patil",
    "email": "harshvardhan.patil@verveadvisory.com",
    "displayName": "Harshvardhan Patil",
    "teamId": "team7",
    "isManager": false,
    "clues": {
      "hobbies": [],
      "quirks": [],
      "funFacts": []
    }
  },
  {
    "id": "trinath.kethavath",
    "email": "trinath.kethavath@verveadvisory.com",
    "displayName": "Trinath Kethavath",
    "teamId": "team7",
    "isManager": false,
    "clues": {
      "hobbies": [],
      "quirks": [],
      "funFacts": []
    }
  },
  {
    "id": "shubhangi",
    "email": "shubhangi@verveadvisory.com",
    "displayName": "Shubhangi",
    "teamId": "team7",
    "isManager": false,
    "clues": {
      "hobbies": [],
      "quirks": [],
      "funFacts": []
    }
  },
  {
    "id": "kajal.yadav",
    "email": "kajal.yadav@verveadvisory.com",
    "displayName": "Kajal Yadav",
    "teamId": "team7",
    "isManager": false,
    "clues": {
      "hobbies": [],
      "quirks": [],
      "funFacts": []
    }
  },
  {
    "id": "aastha.chandwani",
    "email": "aastha.chandwani@verveadvisory.com",
    "displayName": "Aastha Chandwani",
    "teamId": "team7",
    "isManager": false,
    "clues": {
      "hobbies": [],
      "quirks": [],
      "funFacts": []
    }
  },
  {
    "id": "anjali.yadav",
    "email": "anjali.yadav@verveadvisory.com",
    "displayName": "Anjali Yadav",
    "teamId": "team8",
    "isManager": true,
    "clues": {
      "hobbies": [],
      "quirks": [],
      "funFacts": []
    }
  },
  {
    "id": "pratik.nilakhe",
    "email": "pratik.nilakhe@verveadvisory.com",
    "displayName": "Pratik Nilakhe",
    "teamId": "team8",
    "isManager": false,
    "clues": {
      "hobbies": [],
      "quirks": [],
      "funFacts": []
    }
  },
  {
    "id": "vidya.khandelwal",
    "email": "vidya.khandelwal@verveadvisory.com",
    "displayName": "Vidya Khandelwal",
    "teamId": "team8",
    "isManager": false,
    "clues": {
      "hobbies": [],
      "quirks": [],
      "funFacts": []
    }
  },
  {
    "id": "atharv.kale",
    "email": "atharv.kale@verveadvisory.com",
    "displayName": "Atharv Kale",
    "teamId": "team8",
    "isManager": false,
    "clues": {
      "hobbies": [],
      "quirks": [],
      "funFacts": []
    }
  },
  {
    "id": "shailesh.chavan",
    "email": "shailesh.chavan@verveadvisory.com",
    "displayName": "Shailesh Chavan",
    "teamId": "team8",
    "isManager": false,
    "clues": {
      "hobbies": [],
      "quirks": [],
      "funFacts": []
    }
  },
  {
    "id": "rajvir.arya",
    "email": "rajvir.arya@verveadvisory.com",
    "displayName": "Rajvir Arya",
    "teamId": "team8",
    "isManager": false,
    "clues": {
      "hobbies": [],
      "quirks": [],
      "funFacts": []
    }
  },
  {
    "id": "rajat.sonkar",
    "email": "rajat.sonkar@verveadvisory.com",
    "displayName": "Rajat Sonkar",
    "teamId": "team8",
    "isManager": false,
    "clues": {
      "hobbies": [],
      "quirks": [],
      "funFacts": []
    }
  },
  {
    "id": "pooja.mahto",
    "email": "pooja.mahto@verveadvisory.com",
    "displayName": "Pooja Mahto",
    "teamId": "team8",
    "isManager": false,
    "clues": {
      "hobbies": [],
      "quirks": [],
      "funFacts": []
    }
  },
  {
    "id": "om.anil.bhombe",
    "email": "om.bhombe@verveadvisory.com",
    "displayName": "Om Anil Bhombe",
    "teamId": "team8",
    "isManager": false,
    "clues": {
      "hobbies": [],
      "quirks": [],
      "funFacts": []
    }
  }
]
